dryrun/__init__.py
dryrun-1.0.1.dist-info/METADATA
dryrun-1.0.1.dist-info/WHEEL
dryrun-1.0.1.dist-info/top_level.txt
dryrun-1.0.1.dist-info/RECORD
