Metadata-Version: 2.1
Name: dryrun
Version: 1.0.1
Summary: Very awesome dryrun module for python
Home-page: https://github.com/uhmseohun/dryrun-python
Author: Seohun Uhm
Author-email: uhmseohun@gmail.com
License: UNKNOWN
Platform: UNKNOWN
Classifier: Programming Language :: Python :: 3
Classifier: License :: OSI Approved :: MIT License
Classifier: Operating System :: OS Independent
Requires-Python: >=3
